hub77_manager/__init__.py
hub77_manager/client_manager.py
hub77_manager-0.1.3.dist-info/METADATA
hub77_manager-0.1.3.dist-info/WHEEL
hub77_manager-0.1.3.dist-info/top_level.txt
hub77_manager-0.1.3.dist-info/RECORD
