Metadata-Version: 2.1
Name: hub77_manager
Version: 0.1.3
Summary: Facilitador para hub das automações e scraper
Home-page: https://github.com/77-Indicadores/modulo_hubdados
Author: Vinicius Moreira
Author-email: vinicius@77indicadores.com.br
Classifier: Programming Language :: Python :: 3
Classifier: License :: OSI Approved :: MIT License
Classifier: Operating System :: OS Independent
Requires-Python: >=3.8
Requires-Dist: requests>=2.0.0
